[
{
  "id": "810f8610-98d1-432a-9479-e51cc640059e",
  "date": "2026-03-17",
  "description": "Don billet Célio",
  "amountCents": 73215
},
{
  "id": "445ed0be-d7ee-4f8a-bacb-d3eec1b602d5",
  "date": "2026-03-17",
  "description": "Don billet Hamza",
  "amountCents": 76455
},
{
  "id": "2e4cd30f-01f3-4ec6-b92a-7aa0dd78ff13",
  "date": "2026-03-17",
  "description": "Don billets et autres",
  "amountCents": 288530
},
{
  "id": "959fb904-e89e-4cbf-9a77-9fe0b4611568",
  "date": "2026-03-17",
  "description": "Don billets et autres",
  "amountCents": 122215
},
{
  "id": "45a5ff62-1b1c-40e5-afa8-6dfb0f3b0d0b",
  "date": "2026-03-17",
  "description": "Don billets et autres",
  "amountCents": 73300
},
{
  "id": "entry_8ef1f24e-f4d2-42ec-aa52-0cf630a64d07",
  "date": "2026-03-17",
  "description": "Total Mission",
  "amountCents": -931426
}
]
